collabinsightextractor/__init__.py
collabinsightextractor/main.py
collabinsightextractor/prompts.py
collabinsightextractor-2025.12.20201906.dist-info/METADATA
collabinsightextractor-2025.12.20201906.dist-info/WHEEL
collabinsightextractor-2025.12.20201906.dist-info/top_level.txt
collabinsightextractor-2025.12.20201906.dist-info/RECORD
