Metadata-Version: 2.4
Name: collabinsightextractor
Version: 2025.12.20201906
Summary: A new package that processes user-provided text (such as blog posts, articles, or notes) and extracts structured insights about remote team collaboration, based on patterns learned from volunteer open
Author-email: collabinsightextractor <hi@eugene.plus>
License: MIT
Project-URL: Homepage, https://github.com/chigwell/collabinsightextractor
Requires-Python: >=3.9
Requires-Dist: langchain-llm7>=0.0.0
Requires-Dist: llmatch-messages>=0.0.0
Requires-Dist: langchain-core>=0.3.0
